LingzuWenku/README.md
LingzuWenku/__init__.py
LingzuWenku/__main__.py
LingzuWenku/file.epub
LingzuWenku/index.html
LingzuWenku/css/__init__.py
LingzuWenku/css/annotations.css
LingzuWenku/css/main.css
LingzuWenku/css/normalize.css
LingzuWenku/css/popup.css
LingzuWenku/font/__init__.py
LingzuWenku/font/fontello.eot
LingzuWenku/font/fontello.svg
LingzuWenku/font/fontello.ttf
LingzuWenku/font/fontello.woff
LingzuWenku/img/__init__.py
LingzuWenku/img/annotator-glyph-sprite.png
LingzuWenku/img/annotator-icon-sprite.png
LingzuWenku/img/apple-touch-icon.png
LingzuWenku/img/cancelfullscreen.png
LingzuWenku/img/close.png
LingzuWenku/img/fullscreen.png
LingzuWenku/img/loader.gif
LingzuWenku/img/menu-icon.png
LingzuWenku/img/save.png
LingzuWenku/img/saved.png
LingzuWenku/img/settings-s.png
LingzuWenku/img/settings.png
LingzuWenku/img/star.png
LingzuWenku/js/__init__.py
LingzuWenku/js/epub.js
LingzuWenku/js/epub.min.js
LingzuWenku/js/epub.min.map
LingzuWenku/js/hooks.min.js
LingzuWenku/js/hooks.min.map
LingzuWenku/js/reader.js
LingzuWenku/js/reader.js.map
LingzuWenku/js/reader.min.js
LingzuWenku/js/reader.min.map
LingzuWenku/js/hooks/__init__.py
LingzuWenku/js/hooks/extensions/__init__.py
LingzuWenku/js/hooks/extensions/highlight.js
LingzuWenku/js/libs/__init__.py
LingzuWenku/js/libs/jquery.min.js
LingzuWenku/js/libs/localforage.min.js
LingzuWenku/js/libs/screenfull.js
LingzuWenku/js/libs/screenfull.min.js
LingzuWenku/js/libs/zip.min.js
LingzuWenku/js/plugins/__init__.py
LingzuWenku/js/plugins/hypothesis.js
LingzuWenku/js/plugins/search.js
lingzu_wenku-2024.3.6.0.dist-info/METADATA
lingzu_wenku-2024.3.6.0.dist-info/WHEEL
lingzu_wenku-2024.3.6.0.dist-info/entry_points.txt
lingzu_wenku-2024.3.6.0.dist-info/top_level.txt
lingzu_wenku-2024.3.6.0.dist-info/RECORD
